MANIFEST.in
README.rst
setup.py
supervise.py
supervise.egg-info/PKG-INFO
supervise.egg-info/SOURCES.txt
supervise.egg-info/dependency_links.txt
supervise.egg-info/top_level.txt