Metadata-Version: 1.1
Name: supervise
Version: 1.1.1
Summary: Tools for communicating with runit / daemontools supervisors.
Home-page: http://github.com/fmoo/python-supervise
Author: Peter Ruibal
Author-email: ruibalp@gmail.com
License: ISC
Download-URL: https://github.com/fmoo/python-supervise/archive/1.1.1.tar.gz
Keywords: supervise runit daemontools
Platform: UNKNOWN
Classifier: Development Status :: 5 - Production/Stable
Classifier: Topic :: Software Development :: Libraries
Classifier: License :: OSI Approved :: ISC License (ISCL)
